gerritstats/__init__.py
gerritstats/main.py
gerritstats/cmd/__init__.py
gerritstats/cmd/argument.py
gerritstats/cmd/version.py
gerritstats/config/__init__.py
gerritstats/config/config.json
gerritstats/gerrit/__init__.py
gerritstats/gerrit/gerrit.py
gerritstats/logger/__init__.py
gerritstats/logger/logger.py
gerritstats/printer/__init__.py
gerritstats/printer/printer.py
gerritstats/proto/__init__.py
gerritstats/proto/proto.py
gerritstats/querier/__init__.py
gerritstats/querier/querier.py
gerritstats-1.1.0.dist-info/LICENSE
gerritstats-1.1.0.dist-info/METADATA
gerritstats-1.1.0.dist-info/WHEEL
gerritstats-1.1.0.dist-info/entry_points.txt
gerritstats-1.1.0.dist-info/top_level.txt
gerritstats-1.1.0.dist-info/RECORD
