Metadata-Version: 2.1
Name: gerritstats
Version: 1.1.0
Summary: Gerrit Stats
Home-page: https://github.com/craftslab/gerritstats
Author: Jia Jia
Author-email: angersax@sina.com
License: Apache-2.0
Download-URL: https://github.com/craftslab/gerritstats/archive/v1.1.0.tar.gz
Keywords: gerrit,stats
Platform: UNKNOWN
Classifier: Programming Language :: Python :: 3
Classifier: License :: OSI Approved :: Apache Software License
Classifier: Operating System :: OS Independent
License-File: LICENSE
Requires-Dist: black
Requires-Dist: flake8
Requires-Dist: colorama
Requires-Dist: coverage
Requires-Dist: coveralls
Requires-Dist: hypothesis
Requires-Dist: openpyxl
Requires-Dist: mypy
Requires-Dist: pre-commit
Requires-Dist: pytest
Requires-Dist: requests
Requires-Dist: setuptools
Requires-Dist: twine
Requires-Dist: wheel
